Metadata-Version: 2.1
Name: tablify-csv
Version: 0.2.0
Summary: CLI tool that turns a CSV file into an HTML table with basic formatting
Home-page: https://github.com/ralphqq/tablify-csv
Author: Ralph Quirequire
Author-email: ralph.quirequire2012@gmail.com
License: MIT License
Keywords: csv html table conversionformatter converter parser
Platform: UNKNOWN
Classifier: Development Status :: 5 - Production/Stable
Classifier: Environment :: Console
Classifier: Intended Audience :: Developers
Classifier: Programming Language :: Python :: 3.8
Classifier: Operating System :: OS Independent
Requires-Python: >=3.8
Provides-Extra: tests
